[{
	
	"first_name": "Reynolds",
	"last_name": "Scrooby",
	"email": "rscrooby0@noaa.gov",
	"phone": "777-335-0142"
  }, {
	
	"first_name": "Dinnie",
	"last_name": "Kyncl",
	"email": "dkyncl1@symantec.com",
	"phone": "479-653-6095"
  }, {
	
	"first_name": "Ursula",
	"last_name": "MacMenamy",
	"email": "umacmenamy2@furl.net",
	"phone": "439-158-9682"
  }, {
	
	"first_name": "Maxwell",
	"last_name": "Seeks",
	"email": "mseeks3@indiegogo.com",
	"phone": "701-112-5210"
  }, {

	"first_name": "Vonni",
	"last_name": "McCaster",
	"email": "vmccaster4@posterous.com",
	"phone": "577-599-0096"
  }]